Workbook

Sheet Assumptions
A1: Assumptions & Calibration Inputs
A3: Assumption | B3: Value | C3: Type | D3: Source / Basis
A4: Dabur FY2025 total A&P spend (Rs crore) | B4: 864.64 | C4: REAL | D4: BestMediaInfo, 7-May-2025 (see Read Me tab)
A5: Dabur FY2025 consolidated revenue (Rs crore) | B5: 12563 | C5: REAL | D5: Moneycontrol, Storyboard18, 7-May-2025 (see Read Me tab)
A6: A&P spend as % of revenue (implied) | B6: =B4/B5 -> 0.068824325 | C6: FORMULA | D6: 864.64 / 12563 — matches ~7% cited by MatrixBCG
A7: Immunity & Wellness range share of total A&P budget | B7: 0.08 | C7: ASSUMPTION | D7: Analyst assumption for portfolio scoping — not disclosed by Dabur
A8: Implied annual category marketing budget (Rs crore) | B8: =B4*B7 -> 69.1712 | C8: FORMULA | D8: Equals Total A&P spend x category share
A10: Traditional Media (TV+Print) average share of category budget | B10: 0.35 | C10: ASSUMPTION | D10: Modeled starting mix
A11: Digital Display & Search average share of category budget | B11: 0.27 | C11: ASSUMPTION | D11: Modeled starting mix
A12: Influencer/Social average share of category budget | B12: 0.26 | C12: ASSUMPTION | D12: Modeled starting mix, weighted up given Gen-Z focus
A13: Trade Promo & Sampling average share of category budget | B13: 0.12 | C13: ASSUMPTION | D13: Modeled starting mix
A15: Adstock decay rate — Traditional Media | B15: 0.5 | C15: ASSUMPTION | D15: Higher carryover typical of mass broadcast media (industry rule-of-thumb range 0.3-0.7)
A16: Adstock decay rate — Digital Display & Search | B16: 0.3 | C16: ASSUMPTION | D16: Faster decay — search/display intent is largely immediate
A17: Adstock decay rate — Influencer/Social | B17: 0.45 | C17: ASSUMPTION | D17: Moderate carryover — content resurfaces via shares/algorithm for a few weeks
A18: Adstock decay rate — Trade Promo & Sampling | B18: 0.15 | C18: ASSUMPTION | D18: Very fast decay — promo-driven purchase is largely immediate
A20: Base monthly category sales before marketing effect (Rs crore) | B20: 45 | C20: ASSUMPTION | D20: Modeled baseline; anchors the regression intercept to a plausible category size
A21: Seasonality uplift — Oct to Feb (immunity season) | B21: 0.18 | C21: ASSUMPTION | D21: Reflects real seasonal immunity-category demand pattern (winter cold/flu season in India)
A22: Seasonality discount — Jun to Aug (monsoon/low season) | B22: -0.1 | C22: ASSUMPTION | D22: Reflects lower discretionary wellness purchase in monsoon months
A24: Legend: blue fill = real disclosed figure | yellow fill = analyst assumption (edit freely) | black = live formula

Sheet Monthly Data
A1: Month | B1: Traditional Media (TV+Print) | C1: Digital Display & Search | D1: Influencer/Social | E1: Trade Promo & Sampling | F1: Total Spend | G1: Sales (Rs Cr)
A2: Apr-24 | B2: 2.263 | C2: 0.872 | D2: 1.672 | E2: 0.941 | F2: =SUM(B2:E2) -> 5.748 | G2: 56.03
A3: May-24 | B3: 1.597 | C3: 1.348 | D3: 1.723 | E3: 0.89 | F3: =SUM(B3:E3) -> 5.558 | G3: 58.77
A4: Jun-24 | B4: 1.499 | C4: 1.59 | D4: 1.605 | E4: 0.507 | F4: =SUM(B4:E4) -> 5.201 | G4: 58.97
A5: Jul-24 | B5: 1.946 | C5: 1.077 | D5: 1.428 | E5: 0.919 | F5: =SUM(B5:E5) -> 5.37 | G5: 58.97
A6: Aug-24 | B6: 2.078 | C6: 1.629 | D6: 2.126 | E6: 0.682 | F6: =SUM(B6:E6) -> 6.515 | G6: 62.96
A7: Sep-24 | B7: 2.316 | C7: 2.089 | D7: 1.878 | E7: 0.74 | F7: =SUM(B7:E7) -> 7.023 | G7: 68.75
A8: Oct-24 | B8: 2.341 | C8: 1.6 | D8: 0.848 | E8: 1.079 | F8: =SUM(B8:E8) -> 5.868 | G8: 73.36
A9: Nov-24 | B9: 1.998 | C9: 2.359 | D9: 1.283 | E9: 0.847 | F9: =SUM(B9:E9) -> 6.487 | G9: 72.72
A10: Dec-24 | B10: 2.719 | C10: 1.359 | D10: 1.686 | E10: 0.567 | F10: =SUM(B10:E10) -> 6.331 | G10: 75.48
A11: Jan-25 | B11: 2.995 | C11: 1.858 | D11: 1.209 | E11: 0.845 | F11: =SUM(B11:E11) -> 6.907 | G11: 76.54
A12: Feb-25 | B12: 2.12 | C12: 1.484 | D12: 0.979 | E12: 0.392 | F12: =SUM(B12:E12) -> 4.975 | G12: 70.58
A13: Mar-25 | B13: 2.386 | C13: 0.834 | D13: 1.447 | E13: 0.54 | F13: =SUM(B13:E13) -> 5.207 | G13: 63.47
... A25: Mar-26 | B25: 1.835 | C25: 1.265 | D25: 1.539 | E25: 0.907 | F25: =SUM(B25:E25) -> 5.546 | G25: 65.18
A26: TOTAL | B26: =SUM(B2:B25) -> 51.348 | C26: =SUM(C2:C25) -> 37.489 | D26: =SUM(D2:D25) -> 39.925 | E26: =SUM(E2:E25) -> 17.037 | F26: =SUM(F2:F25) -> 145.799 | G26: =SUM(G2:G25) -> 1630.99

Sheet Adstock
A1: Month | B1: Traditional Media (TV+Print) | C1: Digital Display & Search | D1: Influencer/Social | E1: Trade Promo & Sampling
A2: ='Monthly Data'!A2 -> Apr-24 | B2: ='Monthly Data'!B2 -> 2.263 | C2: ='Monthly Data'!C2 -> 0.872 | D2: ='Monthly Data'!D2 -> 1.672 | E2: ='Monthly Data'!E2 -> 0.941
A3: ='Monthly Data'!A3 -> May-24 | B3: ='Monthly Data'!B3+Assumptions!$B$15*B2 -> 2.7285 | C3: ='Monthly Data'!C3+Assumptions!$B$16*C2 -> 1.6096 | D3: ='Monthly Data'!D3+Assumptions!$B$17*D2 -> 2.4754 | E3: ='Monthly Data'!E3+Assumptions!$B$18*E2 -> 1.03115
A4: ='Monthly Data'!A4 -> Jun-24 | B4: ='Monthly Data'!B4+Assumptions!$B$15*B3 -> 2.86325 | C4: ='Monthly Data'!C4+Assumptions!$B$16*C3 -> 2.07288 | D4: ='Monthly Data'!D4+Assumptions!$B$17*D3 -> 2.71893 | E4: ='Monthly Data'!E4+Assumptions!$B$18*E3 -> 0.6616725
A5: ='Monthly Data'!A5 -> Jul-24 | B5: ='Monthly Data'!B5+Assumptions!$B$15*B4 -> 3.377625 | C5: ='Monthly Data'!C5+Assumptions!$B$16*C4 -> 1.698864 | D5: ='Monthly Data'!D5+Assumptions!$B$17*D4 -> 2.6515185 | E5: ='Monthly Data'!E5+Assumptions!$B$18*E4 -> 1.0182509
A6: ='Monthly Data'!A6 -> Aug-24 | B6: ='Monthly Data'!B6+Assumptions!$B$15*B5 -> 3.7668125 | C6: ='Monthly Data'!C6+Assumptions!$B$16*C5 -> 2.1386592 | D6: ='Monthly Data'!D6+Assumptions!$B$17*D5 -> 3.3191833 | E6: ='Monthly Data'!E6+Assumptions!$B$18*E5 -> 0.83473763
A7: ='Monthly Data'!A7 -> Sep-24 | B7: ='Monthly Data'!B7+Assumptions!$B$15*B6 -> 4.1994063 | C7: ='Monthly Data'!C7+Assumptions!$B$16*C6 -> 2.7305978 | D7: ='Monthly Data'!D7+Assumptions!$B$17*D6 -> 3.3716325 | E7: ='Monthly Data'!E7+Assumptions!$B$18*E6 -> 0.86521064
A8: ='Monthly Data'!A8 -> Oct-24 | B8: ='Monthly Data'!B8+Assumptions!$B$15*B7 -> 4.4407031 | C8: ='Monthly Data'!C8+Assumptions!$B$16*C7 -> 2.4191793 | D8: ='Monthly Data'!D8+Assumptions!$B$17*D7 -> 2.3652346 | E8: ='Monthly Data'!E8+Assumptions!$B$18*E7 -> 1.2087816
A9: ='Monthly Data'!A9 -> Nov-24 | B9: ='Monthly Data'!B9+Assumptions!$B$15*B8 -> 4.2183516 | C9: ='Monthly Data'!C9+Assumptions!$B$16*C8 -> 3.0847538 | D9: ='Monthly Data'!D9+Assumptions!$B$17*D8 -> 2.3473556 | E9: ='Monthly Data'!E9+Assumptions!$B$18*E8 -> 1.0283172
A10: ='Monthly Data'!A10 -> Dec-24 | B10: ='Monthly Data'!B10+Assumptions!$B$15*B9 -> 4.8281758 | C10: ='Monthly Data'!C10+Assumptions!$B$16*C9 -> 2.2844261 | D10: ='Monthly Data'!D10+Assumptions!$B$17*D9 -> 2.74231 | E10: ='Monthly Data'!E10+Assumptions!$B$18*E9 -> 0.72124759
A11: ='Monthly Data'!A11 -> Jan-25 | B11: ='Monthly Data'!B11+Assumptions!$B$15*B10 -> 5.4090879 | C11: ='Monthly Data'!C11+Assumptions!$B$16*C10 -> 2.5433278 | D11: ='Monthly Data'!D11+Assumptions!$B$17*D10 -> 2.4430395 | E11: ='Monthly Data'!E11+Assumptions!$B$18*E10 -> 0.95318714
A12: ='Monthly Data'!A12 -> Feb-25 | B12: ='Monthly Data'!B12+Assumptions!$B$15*B11 -> 4.8245439 | C12: ='Monthly Data'!C12+Assumptions!$B$16*C11 -> 2.2469984 | D12: ='Monthly Data'!D12+Assumptions!$B$17*D11 -> 2.0783678 | E12: ='Monthly Data'!E12+Assumptions!$B$18*E11 -> 0.53497807
A13: ='Monthly Data'!A13 -> Mar-25 | B13: ='Monthly Data'!B13+Assumptions!$B$15*B12 -> 4.798272 | C13: ='Monthly Data'!C13+Assumptions!$B$16*C12 -> 1.5080995 | D13: ='Monthly Data'!D13+Assumptions!$B$17*D12 -> 2.3822655 | E13: ='Monthly Data'!E13+Assumptions!$B$18*E12 -> 0.62024671
A14: ='Monthly Data'!A14 -> Apr-25 | B14: ='Monthly Data'!B14+Assumptions!$B$15*B13 -> 3.860136 | C14: ='Monthly Data'!C14+Assumptions!$B$16*C13 -> 1.7974299 | D14: ='Monthly Data'!D14+Assumptions!$B$17*D13 -> 3.1620195 | E14: ='Monthly Data'!E14+Assumptions!$B$18*E13 -> 0.73803701
... A25: ='Monthly Data'!A25 -> Mar-26 | B25: ='Monthly Data'!B25+Assumptions!$B$15*B24 -> 4.7150528 | C25: ='Monthly Data'!C25+Assumptions!$B$16*C24 -> 1.7787095 | D25: ='Monthly Data'!D25+Assumptions!$B$17*D24 -> 2.8984986 | E25: ='Monthly Data'!E25+Assumptions!$B$18*E24 -> 1.0320524

Sheet MMM Regression
A1: MMM Regression — LINEST Multiple Regression Output
A2: LINEST coefficients | B2: Coef: Trade Promo | C2: Coef: Influencer/Social | D2: Coef: Digital Disp&Search | E2: Coef: Traditional Media | F2: Intercept
A3: Coefficients / Intercept | B3: {=LINEST('Monthly Data'!G2:G25,Adstock!B2:E25,TRUE(),FALSE())} -> 7.6305886 | C3: 1.8829492 | D3: 4.2014695 | E3: 5.2318767 | F3: 25.532587
A5: Model Fit Diagnostics (Actual vs Predicted)
A6: Month | B6: Actual Sales | C6: Predicted Sales | D6: Residual | E6: Sq. Residual | F6: Sq. Total Deviation
A7: ='Monthly Data'!A2 -> Apr-24 | B7: ='Monthly Data'!G2 -> 56.03 | C7: =$F$3+$E$3*Adstock!B2+$D$3*Adstock!C2+$C$3*Adstock!D2+$B$3*Adstock!E2 -> 51.36468 | D7: =B7-C7 -> 4.6653196 | E7: =D7^2 -> 21.765207 | F7: =(B7-AVERAGE('Monthly Data'!G2:G25))^2 -> 142.2752
A8: ='Monthly Data'!A3 -> May-24 | B8: ='Monthly Data'!G3 -> 58.77 | C8: =$F$3+$E$3*Adstock!B3+$D$3*Adstock!C3+$C$3*Adstock!D3+$B$3*Adstock!E3 -> 59.099782 | D8: =B8-C8 -> -0.32978182 | E8: =D8^2 -> 0.10875605 | F8: =(B8-AVERAGE('Monthly Data'!G2:G25))^2 -> 84.417813
A9: ='Monthly Data'!A4 -> Jun-24 | B9: ='Monthly Data'!G4 -> 58.97 | C9: =$F$3+$E$3*Adstock!B4+$D$3*Adstock!C4+$C$3*Adstock!D4+$B$3*Adstock!E4 -> 59.390458 | D9: =B9-C9 -> -0.42045784 | E9: =D9^2 -> 0.1767848 | F9: =(B9-AVERAGE('Monthly Data'!G2:G25))^2 -> 80.782646
A10: ='Monthly Data'!A5 -> Jul-24 | B10: ='Monthly Data'!G5 -> 58.97 | C10: =$F$3+$E$3*Adstock!B5+$D$3*Adstock!C5+$C$3*Adstock!D5+$B$3*Adstock!E5 -> 63.104158 | D10: =B10-C10 -> -4.134158 | E10: =D10^2 -> 17.091262 | F10: =(B10-AVERAGE('Monthly Data'!G2:G25))^2 -> 80.782646
A11: ='Monthly Data'!A6 -> Aug-24 | B11: ='Monthly Data'!G6 -> 62.96 | C11: =$F$3+$E$3*Adstock!B6+$D$3*Adstock!C6+$C$3*Adstock!D6+$B$3*Adstock!E6 -> 66.84499 | D11: =B11-C11 -> -3.88499 | E11: =D11^2 -> 15.093147 | F11: =(B11-AVERAGE('Monthly Data'!G2:G25))^2 -> 24.979171
A12: ='Monthly Data'!A7 -> Sep-24 | B12: ='Monthly Data'!G7 -> 68.75 | C12: =$F$3+$E$3*Adstock!B7+$D$3*Adstock!C7+$C$3*Adstock!D7+$B$3*Adstock!E7 -> 71.926565 | D12: =B12-C12 -> -3.1765651 | E12: =D12^2 -> 10.090566 | F12: =(B12-AVERAGE('Monthly Data'!G2:G25))^2 -> 0.62739601
A13: ='Monthly Data'!A8 -> Oct-24 | B13: ='Monthly Data'!G8 -> 73.36 | C13: =$F$3+$E$3*Adstock!B8+$D$3*Adstock!C8+$C$3*Adstock!D8+$B$3*Adstock!E8 -> 72.607238 | D13: =B13-C13 -> 0.7527619 | E13: =D13^2 -> 0.56665047 | F13: =(B13-AVERAGE('Monthly Data'!G2:G25))^2 -> 29.182504
A14: ='Monthly Data'!A9 -> Nov-24 | B14: ='Monthly Data'!G9 -> 72.72 | C14: =$F$3+$E$3*Adstock!B9+$D$3*Adstock!C9+$C$3*Adstock!D9+$B$3*Adstock!E9 -> 72.829598 | D14: =B14-C14 -> -0.10959843 | E14: =D14^2 -> 0.012011816 | F14: =(B14-AVERAGE('Monthly Data'!G2:G25))^2 -> 22.677438
A15: ='Monthly Data'!A10 -> Dec-24 | B15: ='Monthly Data'!G10 -> 75.48 | C15: =$F$3+$E$3*Adstock!B10+$D$3*Adstock!C10+$C$3*Adstock!D10+$B$3*Adstock!E10 -> 71.058128 | D15: =B15-C15 -> 4.4218718 | E15: =D15^2 -> 19.55295 | F15: =(B15-AVERAGE('Monthly Data'!G2:G25))^2 -> 56.581738
A16: ='Monthly Data'!A11 -> Jan-25 | B16: ='Monthly Data'!G11 -> 76.54 | C16: =$F$3+$E$3*Adstock!B11+$D$3*Adstock!C11+$C$3*Adstock!D11+$B$3*Adstock!E11 -> 76.39148 | D16: =B16-C16 -> 0.14851956 | E16: =D16^2 -> 0.02205806 | F16: =(B16-AVERAGE('Monthly Data'!G2:G25))^2 -> 73.652154
A17: ='Monthly Data'!A12 -> Feb-25 | B17: ='Monthly Data'!G12 -> 70.58 | C17: =$F$3+$E$3*Adstock!B12+$D$3*Adstock!C12+$C$3*Adstock!D12+$B$3*Adstock!E12 -> 68.21036 | D17: =B17-C17 -> 2.3696404 | E17: =D17^2 -> 5.6151955 | F17: =(B17-AVERAGE('Monthly Data'!G2:G25))^2 -> 6.875321
A18: ='Monthly Data'!A13 -> Mar-25 | B18: ='Monthly Data'!G13 -> 63.47 | C18: =$F$3+$E$3*Adstock!B13+$D$3*Adstock!C13+$C$3*Adstock!D13+$B$3*Adstock!E13 -> 66.191321 | D18: =B18-C18 -> -2.7213208 | E18: =D18^2 -> 7.4055868 | F18: =(B18-AVERAGE('Monthly Data'!G2:G25))^2 -> 20.141396
A19: ='Monthly Data'!A14 -> Apr-25 | B19: ='Monthly Data'!G14 -> 66.76 | C19: =$F$3+$E$3*Adstock!B14+$D$3*Adstock!C14+$C$3*Adstock!D14+$B$3*Adstock!E14 -> 64.865768 | D19: =B19-C19 -> 1.8942319 | E19: =D19^2 -> 3.5881147 | F19: =(B19-AVERAGE('Monthly Data'!G2:G25))^2 -> 1.4350043
A20: ='Monthly Data'!A15 -> May-25 | B20: ='Monthly Data'!G15 -> 65 | C20: =$F$3+$E$3*Adstock!B15+$D$3*Adstock!C15+$C$3*Adstock!D15+$B$3*Adstock!E15 -> 62.80716 | D20: =B20-C20 -> 2.1928401 | E20: =D20^2 -> 4.8085479 | F20: =(B20-AVERAGE('Monthly Data'!G2:G25))^2 -> 8.749271
A21: ='Monthly Data'!A16 -> Jun-25 | B21: ='Monthly Data'!G16 -> 59.56 | C21: =$F$3+$E$3*Adstock!B16+$D$3*Adstock!C16+$C$3*Adstock!D16+$B$3*Adstock!E16 -> 62.693042 | D21: =B21-C21 -> -3.1330422 | E21: =D21^2 -> 9.8159534 | F21: =(B21-AVERAGE('Monthly Data'!G2:G25))^2 -> 70.525004
A22: ='Monthly Data'!A17 -> Jul-25 | B22: ='Monthly Data'!G17 -> 63.08 | C22: =$F$3+$E$3*Adstock!B17+$D$3*Adstock!C17+$C$3*Adstock!D17+$B$3*Adstock!E17 -> 66.652776 | D22: =B22-C22 -> -3.5727756 | E22: =D22^2 -> 12.764725 | F22: =(B22-AVERAGE('Monthly Data'!G2:G25))^2 -> 23.794071
A23: ='Monthly Data'!A18 -> Aug-25 | B23: ='Monthly Data'!G18 -> 65.21 | C23: =$F$3+$E$3*Adstock!B18+$D$3*Adstock!C18+$C$3*Adstock!D18+$B$3*Adstock!E18 -> 70.213296 | D23: =B23-C23 -> -5.0032961 | E23: =D23^2 -> 25.032972 | F23: =(B23-AVERAGE('Monthly Data'!G2:G25))^2 -> 7.551046
A24: ='Monthly Data'!A19 -> Sep-25 | B24: ='Monthly Data'!G19 -> 68.93 | C24: =$F$3+$E$3*Adstock!B19+$D$3*Adstock!C19+$C$3*Adstock!D19+$B$3*Adstock!E19 -> 70.479173 | D24: =B24-C24 -> -1.5491728 | E24: =D24^2 -> 2.3999363 | F24: =(B24-AVERAGE('Monthly Data'!G2:G25))^2 -> 0.94494601
A25: ='Monthly Data'!A20 -> Oct-25 | B25: ='Monthly Data'!G20 -> 76.06 | C25: =$F$3+$E$3*Adstock!B20+$D$3*Adstock!C20+$C$3*Adstock!D20+$B$3*Adstock!E20 -> 71.760812 | D25: =B25-C25 -> 4.2991882 | E25: =D25^2 -> 18.483019 | F25: =(B25-AVERAGE('Monthly Data'!G2:G25))^2 -> 65.643754
A26: ='Monthly Data'!A21 -> Nov-25 | B26: ='Monthly Data'!G21 -> 79.3 | C26: =$F$3+$E$3*Adstock!B21+$D$3*Adstock!C21+$C$3*Adstock!D21+$B$3*Adstock!E21 -> 73.304349 | D26: =B26-C26 -> 5.9956507 | E26: =D26^2 -> 35.947827 | F26: =(B26-AVERAGE('Monthly Data'!G2:G25))^2 -> 128.64285
A27: ='Monthly Data'!A22 -> Dec-25 | B27: ='Monthly Data'!G22 -> 75.55 | C27: =$F$3+$E$3*Adstock!B22+$D$3*Adstock!C22+$C$3*Adstock!D22+$B$3*Adstock!E22 -> 69.685386 | D27: =B27-C27 -> 5.8646142 | E27: =D27^2 -> 34.393699 | F27: =(B27-AVERAGE('Monthly Data'!G2:G25))^2 -> 57.639729
A28: ='Monthly Data'!A23 -> Jan-26 | B28: ='Monthly Data'!G23 -> 75.52 | C28: =$F$3+$E$3*Adstock!B23+$D$3*Adstock!C23+$C$3*Adstock!D23+$B$3*Adstock!E23 -> 73.588948 | D28: =B28-C28 -> 1.9310521 | E28: =D28^2 -> 3.7289622 | F28: =(B28-AVERAGE('Monthly Data'!G2:G25))^2 -> 57.185104
A29: ='Monthly Data'!A24 -> Feb-26 | B29: ='Monthly Data'!G24 -> 74.24 | C29: =$F$3+$E$3*Adstock!B24+$D$3*Adstock!C24+$C$3*Adstock!D24+$B$3*Adstock!E24 -> 74.913283 | D29: =B29-C29 -> -0.67328302 | E29: =D29^2 -> 0.45331003 | F29: =(B29-AVERAGE('Monthly Data'!G2:G25))^2 -> 39.464571
A30: ='Monthly Data'!A25 -> Mar-26 | B30: ='Monthly Data'!G25 -> 65.18 | C30: =$F$3+$E$3*Adstock!B25+$D$3*Adstock!C25+$C$3*Adstock!D25+$B$3*Adstock!E25 -> 71.007249 | D30: =B30-C30 -> -5.8272488 | E30: =D30^2 -> 33.956829 | F30: =(B30-AVERAGE('Monthly Data'!G2:G25))^2 -> 7.716821
A31: SUM | E31: =SUM(E7:E30) -> 282.87407 | F31: =SUM(F7:F30) -> 1092.2676
A33: R-squared | B33: =1-(E31/F31) -> 0.74102127
A34: F-statistic (k=4 predictors, n=24 months) | B34: =(B33/4)/((1-B33)/(24-4-1)) -> 13.591275
A37: Channel Contribution & ROI
A38: Channel | B38: Coefficient (Rs Cr sales per Rs Cr adstocked spend) | C38: Total Spend (Rs Cr, 24mo) | D38: Attributed Sales (Rs Cr) | E38: Contribution % | F38: ROI (x)
A39: Traditional Media (TV+Print) | B39: =E3 -> 5.2318767 | C39: ='Monthly Data'!B26 -> 51.348 | D39: =B39*SUM(Adstock!B2:B25) -> 512.62423 | E39: =D39/$D$43 -> 0.50345733 | F39: =D39/C39 -> 9.9833339
A40: Digital Display & Search | B40: =D3 -> 4.2014695 | C40: ='Monthly Data'!C26 -> 37.489 | D40: =B40*SUM(Adstock!C2:C25) -> 221.80991 | E40: =D40/$D$43 -> 0.21784343 | F40: =D40/C40 -> 5.9166664
A41: Influencer/Social | B41: =C3 -> 1.8829492 | C41: ='Monthly Data'!D26 -> 39.925 | D41: =B41*SUM(Adstock!D2:D25) -> 132.21958 | E41: =D41/$D$43 -> 0.12985519 | F41: =D41/C41 -> 3.311699
A42: Trade Promo & Sampling | B42: =B3 -> 7.6305886 | C42: ='Monthly Data'!E26 -> 17.037 | D42: =B42*SUM(Adstock!E2:E25) -> 151.55419 | E42: =D42/$D$43 -> 0.14884405 | F42: =D42/C42 -> 8.8955914
A43: TOTAL (marketing-attributed) | C43: =SUM(C39:C42) -> 145.799 | D43: =SUM(D39:D42) -> 1018.2079
A44: Base sales (non-marketing, intercept x 24mo) | D44: =F3*24 -> 612.78209

Sheet Budget Reallocation
A1: Budget Reallocation What-If Scenario
A2: Edit the yellow 'Shift (Rs Cr)' cells to move annual budget between channels. Projected incremental sales use each channel's MMM-derived ROI. Shifts must net to zero.
A4: Channel | B4: Current Annual Spend (Rs Cr) | C4: Shift (Rs Cr) | D4: New Annual Spend (Rs Cr) | E4: ROI (x) | F4: Incremental Sales from Shift (Rs Cr)
A5: Traditional Media (TV+Print) | B5: ='MMM Regression'!C39 -> 51.348 | C5: 3 | D5: =B5+C5 -> 54.348 | E5: ='MMM Regression'!F39 -> 9.9833339 | F5: =C5*E5 -> 29.950002
A6: Digital Display & Search | B6: ='MMM Regression'!C40 -> 37.489 | C6: 0 | D6: =B6+C6 -> 37.489 | E6: ='MMM Regression'!F40 -> 5.9166664 | F6: =C6*E6 -> 0
A7: Influencer/Social | B7: ='MMM Regression'!C41 -> 39.925 | C7: -3 | D7: =B7+C7 -> 36.925 | E7: ='MMM Regression'!F41 -> 3.311699 | F7: =C7*E7 -> -9.9350969
A8: Trade Promo & Sampling | B8: ='MMM Regression'!C42 -> 17.037 | C8: 0 | D8: =B8+C8 -> 17.037 | E8: ='MMM Regression'!F42 -> 8.8955914 | F8: =C8*E8 -> 0
A9: TOTAL / NET | B9: =SUM(B5:B8) -> 145.799 | C9: =SUM(C5:C8) -> 0 | D9: =SUM(D5:D8) -> 145.799 | F9: =SUM(F5:F8) -> 20.014905
A10: Balance check (should be 0) | C10: =C9 -> 0
A12: Net projected incremental sales from reallocation (Rs Cr) | F12: =F9 -> 20.014905
A15: Example scenario already entered: shift Rs 3 Cr from Influencer/Social to Traditional Media — the lowest- and highest-ROI channels in THIS dataset (edit freely, and re-check the ROI column if you change assumptions, since which channel is 'best' can change).

Sheet GTM Research Plan
A1: Primary Research Plan — Gen-Z Wellness Survey (fill in real data)
A2: This tab is a TEMPLATE, not simulated data — go run this survey for real (Google Forms works well), aiming for 100+ respondents + 8-10 follow-up interviews, mirroring your Lakme L.I.M.E. project methodology. Tally real responses into the yellow cells below.
A4: SURVEY QUESTIONS (target: Gen-Z, ages 18-27)
A5: Q1. How often do you consume wellness/immunity products (chyawanprash, health drinks, supplements)? (Never / Occasionally / Regularly)
A6: Q2. What comes to mind when you hear 'Dabur' or 'Chyawanprash'? (Open-ended)
A7: Q3. Do you associate Ayurvedic wellness brands with being 'for young people' or 'for parents/grandparents'?
A8: Q4. Which factors matter most when choosing a wellness product? (Taste/format, Price, Scientific backing, Brand trust, Recommendation from influencer/friend)
A9: Q5. Which platforms do you discover new wellness/health products on? (Instagram, YouTube, TikTok-equivalent, Word of mouth, In-store)
A10: Q6. Would you try a modern format of a traditional wellness product (e.g., gummies, shots, on-the-go sachets)? (Yes/No/Maybe)
A11: Q7. How important is sustainability/clean-label messaging in your purchase decision? (1-5 scale)
A12: Q8. Net Promoter-style: How likely are you to recommend an Ayurvedic wellness brand to a friend? (0-10)
A14: RESPONSE TALLY TEMPLATE (paste your real survey results here)
A15: Question | B15: Option A | C15: Option B | D15: Option C | E15: Option D
A16: Q1 - Consumption frequency (%)
A17: Q3 - Young vs Parents association (%)
A18: Q4 - Top purchase factor (%)
A19: Q5 - Discovery platform (%)
A20: Q6 - Willing to try modern format (%)
A23: INTERVIEW GUIDE (8-10 respondents, 15-20 min each)
A24: - Walk me through the last time you bought/consumed a wellness or immunity product.
A25: - What would make an Ayurvedic brand feel 'made for you' rather than 'made for your parents'?
A26: - Show a mock modern-format product (gummy/shot). Get unprompted reaction, then probe on price sensitivity and repeat-purchase likelihood.
A29: POSITIONING FRAMEWORK (fill in after research — Insight/Tension/Resolution, same as Lakme project)
A30: Insight:
A31: Tension:
A32: Resolution:
